llama_index/readers/readme/BUILD
llama_index/readers/readme/__init__.py
llama_index/readers/readme/base.py
llama_index_readers_readme-0.3.0.dist-info/METADATA
llama_index_readers_readme-0.3.0.dist-info/WHEEL
llama_index_readers_readme-0.3.0.dist-info/RECORD
