Metadata-Version: 2.1
Name: llama-index-readers-readme
Version: 0.3.0
Summary: llama-index readers readme.com integration
License: MIT
Author: Gonzalo Rios
Author-email: contacto@gonzalorios.cl
Requires-Python: >=3.9,<4.0
Classifier: License :: OSI Approved :: MIT License
Classifier: Programming Language :: Python :: 3
Classifier: Programming Language :: Python :: 3.9
Classifier: Programming Language :: Python :: 3.10
Classifier: Programming Language :: Python :: 3.11
Classifier: Programming Language :: Python :: 3.12
Requires-Dist: beautifulsoup4 (>=4.12.3,<5.0.0)
Requires-Dist: llama-index-core (>=0.12.0,<0.13.0)
Requires-Dist: requests (>=2.31.0,<3.0.0)
